django_ddd_template/__init__.py
django_ddd_template/cli.py
django_ddd_template/templates_registry.py
django_ddd_template/management/__init__.py
django_ddd_template/management/commands/__init__.py
django_ddd_template/management/commands/startapp_ddd.py
django_ddd_template/templates/__init__.py
django_ddd_template/templates/ddd_app/__init__.py
django_ddd_template/templates/ddd_app/domain/__init__.py
django_ddd_template/templates/ddd_app/domain/entities/__init__.py
django_ddd_template/templates/ddd_app/domain/repositories/__init__.py
django_ddd_template/templates/ddd_app/domain/services/__init__.py
django_ddd_template/templates/ddd_app/infrastructure/__init__.py
django_ddd_template/templates/ddd_app/infrastructure/models/__init__.py
django_ddd_template/templates/ddd_app/infrastructure/repositories/__init__.py
django_ddd_template/templates/ddd_app/infrastructure/serializers/__init__.py
django_ddd_template/templates/ddd_app/infrastructure/views/__init__.py
django_ddd_template/templates/ddd_app/migrations/__init__.py
django_ddd_template/templates/ddd_app/tests/__init__.py
django_ddd_template-2.0.2.dist-info/METADATA
django_ddd_template-2.0.2.dist-info/WHEEL
django_ddd_template-2.0.2.dist-info/entry_points.txt
django_ddd_template-2.0.2.dist-info/top_level.txt
django_ddd_template-2.0.2.dist-info/RECORD
