Metadata-Version: 2.4
Name: django-ddd-template
Version: 2.0.2
Summary: Crea apps Django con arquitectura DDD
Author: Osmel Mojena Dubet
License: MIT
Requires-Dist: Django>=3.2
Dynamic: author
Dynamic: description
Dynamic: description-content-type
Dynamic: license
Dynamic: requires-dist
Dynamic: summary
